orbitcontrol_patch/__init__.py
orbitcontrol_patch/_version.py
orbitcontrol_patch/example.py
orbitcontrol_patch/orbitcontrol.py
orbitcontrol_patch/labextension/build_log.json
orbitcontrol_patch/labextension/package.json
orbitcontrol_patch/labextension/static/261.d271d577a9dceb70b596.js
orbitcontrol_patch/labextension/static/568.bbaec5b762c2b6004052.js
orbitcontrol_patch/labextension/static/961.554a9257e4659fa070d0.js
orbitcontrol_patch/labextension/static/961.554a9257e4659fa070d0.js.LICENSE.txt
orbitcontrol_patch/labextension/static/lib_index_js.558ccc9e8b1ae41712d6.js
orbitcontrol_patch/labextension/static/lib_index_js.68ebafdb93792e2242c3.js
orbitcontrol_patch/labextension/static/lib_index_js.7a28d18503e15a54bdbe.js
orbitcontrol_patch/labextension/static/lib_labplugin_js.0ba8c241d71f6b86bd5d.js
orbitcontrol_patch/labextension/static/lib_labplugin_js.78d4f37486031dccce4d.js
orbitcontrol_patch/labextension/static/lib_labplugin_js.7ea37fc9bf3dbb4246ac.js
orbitcontrol_patch/labextension/static/remoteEntry.1497ee00954305a7151e.js
orbitcontrol_patch/labextension/static/remoteEntry.6cace98954848997be48.js
orbitcontrol_patch/labextension/static/remoteEntry.7e438af8d73388599ba5.js
orbitcontrol_patch/labextension/static/remoteEntry.b68d4c63417a93b52110.js
orbitcontrol_patch/labextension/static/style.js
orbitcontrol_patch/labextension/static/vendors-node_modules_jupyter-threejs_dist_index_js.2da076969a0e5ae36ebe.js
orbitcontrol_patch/nbextension/extension.js
orbitcontrol_patch/nbextension/index.js
orbitcontrol_patch/nbextension/index.js.LICENSE.txt
orbitcontrol_patch-0.1.0.data/data/etc/jupyter/nbconfig/notebook.d/orbitcontrol_patch.json
orbitcontrol_patch-0.1.0.data/data/share/jupyter/labextensions/orbitcontrol_patch/build_log.json
orbitcontrol_patch-0.1.0.data/data/share/jupyter/labextensions/orbitcontrol_patch/install.json
orbitcontrol_patch-0.1.0.data/data/share/jupyter/labextensions/orbitcontrol_patch/package.json
orbitcontrol_patch-0.1.0.dist-info/METADATA
orbitcontrol_patch-0.1.0.dist-info/WHEEL
orbitcontrol_patch-0.1.0.dist-info/top_level.txt
orbitcontrol_patch-0.1.0.dist-info/RECORD
