Metadata-Version: 2.1
Name: orbitcontrol-patch
Version: 0.1.0
Summary: A patch for pythreejs Orbitcontrol to update at init
Home-page: https://github.com/bernhard-42/orbitcontrol-patch
Author: Bernhard Walter
Author-email: b_walter@arcor.de
License: UNKNOWN
Keywords: ipython,jupyter,widgets
Platform: UNKNOWN
Classifier: Development Status :: 4 - Beta
Classifier: Framework :: IPython
Classifier: Intended Audience :: Developers
Classifier: Intended Audience :: Science/Research
Classifier: Topic :: Multimedia :: Graphics
Classifier: Programming Language :: Python :: 3.6
Classifier: Programming Language :: Python :: 3.7
Classifier: Programming Language :: Python :: 3.8
Classifier: Programming Language :: Python :: 3.9
Requires-Dist: ipywidgets (>=7.6.0)
